<?xml version="1.0" encoding="UTF-8" standalone="no"?><root><pattern25><name>Adapter (class)</name><isprimary>true</isprimary><description>This pattern uses multiple polymophic interfaces to implementing or inheriting both the interface that is expected and the interface that is pre-existing</description><aka0>AC</aka0><diagram>adapterClass.xml</diagram><pros0>Pro1</pros0><cons0>Con1</cons0></pattern25><purpose4><name>Structural</name></purpose4><scope3><name>Class</name></scope3><problem1><description>Problem test</description></problem1><force1><description>Force test</description></force1></root>